compositional_logger/CLogger.py
compositional_logger/__init__.py
compositional_logger-0.1.0.dist-info/LICENSE
compositional_logger-0.1.0.dist-info/METADATA
compositional_logger-0.1.0.dist-info/WHEEL
compositional_logger-0.1.0.dist-info/top_level.txt
compositional_logger-0.1.0.dist-info/RECORD
